libprotein-0.3.6.data/purelib/libprotein/__init__.py
libprotein-0.3.6.data/purelib/libprotein/_libprotein.so
libprotein-0.3.6.data/scripts/mainlibprotein
libprotein-0.3.6.dist-info/METADATA
libprotein-0.3.6.dist-info/WHEEL
libprotein-0.3.6.dist-info/top_level.txt
libprotein-0.3.6.dist-info/RECORD
